manytasks/__init__.py
manytasks/cuda_manager.py
manytasks/defs.py
manytasks/entry.py
manytasks/log_extractor.py
manytasks/task_runner.py
manytasks/taskpool_loader.py
manytasks/util.py
manytasks-2.3.dist-info/METADATA
manytasks-2.3.dist-info/WHEEL
manytasks-2.3.dist-info/entry_points.txt
manytasks-2.3.dist-info/top_level.txt
manytasks-2.3.dist-info/RECORD
