Metadata-Version: 2.1
Name: manytasks
Version: 2.3
Summary: A tool for deploying many tasks automatically.
Home-page: https://github.com/dugu9sword/manytasks
Author: dugu9sword
Author-email: dugu9sword@163.com
License: WTFPL Licence
Keywords: manytasks
Platform: any
Requires-Dist: jstyleson
Requires-Dist: tabulate
Requires-Dist: numpy
Requires-Dist: psutil
Requires-Dist: pyyaml
